fastgui/1.ico
fastgui/__init__.py
fastgui/_matrixgui.py
fastgui/_testgui.py
fastgui-1.0.2.dist-info/METADATA
fastgui-1.0.2.dist-info/WHEEL
fastgui-1.0.2.dist-info/top_level.txt
fastgui-1.0.2.dist-info/RECORD
