Metadata-Version: 2.1
Name: fastgui
Version: 1.0.2
Summary: Gui tool to test py programs.
Home-page: https://github.com/userElaina
Author: userElaina
Author-email: userElaina@google.com
License: UNKNOWN
Keywords: fast gui elaina
Platform: UNKNOWN
Classifier: Programming Language :: Python :: 3
Requires-Python: >=3.6
Requires-Dist: tk
Requires-Dist: downs
